fastuml/__init__.py
fastuml/__main__.py
fastuml/class_options.py
fastuml/uml.py
fastuml/grammar/class_options.tx
fastuml/grammar/class_uml.tx
fastuml/grammar/components/base.tx
fastuml/grammar/components/class_commons.tx
fastuml/grammar/components/options.tx
fastuml/templates/class.jinja
fastuml/templates/connection.jinja
fastuml/templates/package.jinja
fastuml/templates/plantuml.jinja
fastuml/templates/plantuml_class.jinja
fastuml/templates/plantuml_connection.jinja
fastuml/templates/plantuml_package.jinja
fastuml/templates/uml.jinja
fastuml-0.3.1.dist-info/LICENSE
fastuml-0.3.1.dist-info/METADATA
fastuml-0.3.1.dist-info/WHEEL
fastuml-0.3.1.dist-info/entry_points.txt
fastuml-0.3.1.dist-info/top_level.txt
fastuml-0.3.1.dist-info/RECORD
