Metadata-Version: 2.1
Name: fastuml
Version: 0.3.1
Author: Mathis Logemann
Classifier: Programming Language :: Python :: 3
Classifier: License :: OSI Approved :: MIT License
Classifier: Operating System :: OS Independent
Requires-Python: >=3.7
License-File: LICENSE
Requires-Dist: textx
Requires-Dist: Jinja2
Requires-Dist: click
